README.rst
setup.py
xylib.i
xylib.py
xylib/bruker_raw.cpp
xylib/bruker_spc.cpp
xylib/cache.cpp
xylib/canberra_cnf.cpp
xylib/canberra_mca.cpp
xylib/chiplot.cpp
xylib/cpi.cpp
xylib/csv.cpp
xylib/dbws.cpp
xylib/pdcif.cpp
xylib/philips_raw.cpp
xylib/philips_udf.cpp
xylib/riet7.cpp
xylib/rigaku_dat.cpp
xylib/specsxy.cpp
xylib/spectra.cpp
xylib/text.cpp
xylib/util.cpp
xylib/uxd.cpp
xylib/vamas.cpp
xylib/winspec_spe.cpp
xylib/xfit_xdd.cpp
xylib/xrdml.cpp
xylib/xsyg.cpp
xylib/xylib.cpp
xylib_py.egg-info/PKG-INFO
xylib_py.egg-info/SOURCES.txt
xylib_py.egg-info/dependency_links.txt
xylib_py.egg-info/top_level.txt