Metadata-Version: 1.1
Name: xylib-py
Version: 1.6.0
Summary: Python bindings to xylib
Home-page: https://github.com/wojdyr/xylib
Author: Marcin Wojdyr
Author-email: wojdyr@gmail.com
License: LGPL2.1
Platform: UNKNOWN
Classifier: Development Status :: 5 - Production/Stable
Classifier: Intended Audience :: Developers
Classifier: Intended Audience :: Science/Research
Classifier: Programming Language :: Python :: Implementation :: CPython
Classifier: Topic :: Scientific/Engineering :: Chemistry
Classifier: Topic :: Software Development :: Libraries :: Python Modules
